dtlib/__init__.py
dtlib/utils.py
dtlib/trees/BinarySearchTree.py
dtlib/trees/BinaryTree.py
dtlib/trees/Heap.py
dtlib/trees/OrderStatisticTree.py
dtlib/trees/Tree.py
dtlib/trees/WeightBalancedTree.py
dtlib/trees/_ArrayBinarySearchTree.py
dtlib/trees/_ArrayBinaryTree.py
dtlib/trees/_ArrayHeap.py
dtlib/trees/_ArrayOrderStatisticTree.py
dtlib/trees/_ArrayWeightBalancedTree.py
dtlib/trees/_LinkedBinarySearchTree.py
dtlib/trees/_LinkedBinaryTree.py
dtlib/trees/_LinkedHeap.py
dtlib/trees/_LinkedOrderStatisticTree.py
dtlib/trees/_LinkedWeightBalancedTree.py
dtlib/trees/_Node.py
dtlib/trees/__init__.py
dtlib/trees/_config.py
dtlib/trees/_constants.py
dtlib/trees/utils.py
dtlib/trees/tests/__init__.py
dtlib/trees/tests/test_ArrayBinaryTree.py
dtlib/trees/tests/test_Node.py
dtlib-0.0.0.dev2.dist-info/LICENSE
dtlib-0.0.0.dev2.dist-info/METADATA
dtlib-0.0.0.dev2.dist-info/WHEEL
dtlib-0.0.0.dev2.dist-info/top_level.txt
dtlib-0.0.0.dev2.dist-info/RECORD
