Metadata-Version: 2.1
Name: dtlib
Version: 0.0.0.dev2
Summary: A small package of basic data structures and algorithms
Author-email: Jeffrey Bonde <jeffrey.bonde@gmail.com>
License: MIT License        
Project-URL: Homepage, https://github.com/bondeje/dtlib
Project-URL: Bug Tracker, https://github.com/bondeje/dtlib/issues
Classifier: Programming Language :: Python :: 3
Classifier: License :: OSI Approved :: MIT License
Classifier: Operating System :: OS Independent
Requires-Python: >=3.7
License-File: LICENSE
